{"version":1,"resource":"vscode-remote://wsl%2Bubuntu-24.04/home/huong/nhakhoaso/templates/bao_cao_dich_vu.html","entries":[{"id":"16YG.html","source":"Workspace Edit","timestamp":1745257070440},{"id":"01mH.html","source":"Workspace Edit","timestamp":1745258380852},{"id":"2HOr.html","source":"Workspace Edit","timestamp":1745261876486},{"id":"MAzU.html","source":"Workspace Edit","timestamp":1745600713256},{"id":"HcvO.html","source":"Workspace Edit","timestamp":1745601198517},{"id":"VyzQ.html","source":"Workspace Edit","timestamp":1745602346827},{"id":"wOwr.html","source":"Workspace Edit","timestamp":1745603060711},{"id":"oMFD.html","source":"Workspace Edit","timestamp":1745606370166},{"id":"QF2w.html","source":"Workspace Edit","timestamp":1745606776917}]}